{"0": "chitchat/IKnow", "1": "chitchat/Question", "2": "chitchat/ask_age", "3": "chitchat/ask_behavior", "4": "chitchat/ask_create", "5": "chitchat/ask_figure", "6": "chitchat/ask_fiqr", "7": "chitchat/ask_for_stop", "8": "chitchat/ask_fun", "9": "chitchat/ask_inventing", "10": "chitchat/ask_job", "11": "chitchat/ask_name", "12": "chitchat/ask_religion", "13": "chitchat/ask_threatening", "14": "chitchat/give_details", "15": "chitchat/insisting_ask_job", "16": "chitchat/intellegence", "17": "chitchat/na3am", "18": "chitchat/notOkay", "19": "chitchat/not_answer", "20": "chitchat/sure_ar", "21": "chitchat/t2na3", "22": "chitchat/take", "23": "chitchat/what_nobel", "24": "chitchat/\u0643\u064a\u0641\u0643", "25": "chitchat/\u0643\u064a\u0641\u0643 \u062c\u0627\u0643\u061f", "26": "chitchat/\u0645\u0628\u0633\u0648\u0637\u061f"}